ts3l/__init__.py
ts3l/functional/__init__.py
ts3l/functional/dae.py
ts3l/functional/scarf.py
ts3l/functional/subtab.py
ts3l/functional/switchtab.py
ts3l/functional/tabularbinning.py
ts3l/functional/vime.py
ts3l/models/__init__.py
ts3l/models/common/__init__.py
ts3l/models/common/backbone.py
ts3l/models/common/base_model.py
ts3l/models/common/embedding.py
ts3l/models/common/misc.py
ts3l/models/common/mlp.py
ts3l/models/common/reconstruction_head.py
ts3l/models/common/transformer_encoder.py
ts3l/models/dae/__init__.py
ts3l/models/dae/dae.py
ts3l/models/scarf/__init__.py
ts3l/models/scarf/loss.py
ts3l/models/scarf/scarf.py
ts3l/models/subtab/__init__.py
ts3l/models/subtab/loss.py
ts3l/models/subtab/subtab.py
ts3l/models/switchtab/__init__.py
ts3l/models/switchtab/switchtab.py
ts3l/models/tabularbinning/__init__.py
ts3l/models/tabularbinning/tabularbinning.py
ts3l/models/vime/__init__.py
ts3l/models/vime/vime.py
ts3l/models/vime/vime_predictor.py
ts3l/pl_modules/__init__.py
ts3l/pl_modules/base_module.py
ts3l/pl_modules/dae_lightning.py
ts3l/pl_modules/scarf_lightning.py
ts3l/pl_modules/subtab_lightning.py
ts3l/pl_modules/switchtab_lightning.py
ts3l/pl_modules/tabularbinning_lightning.py
ts3l/pl_modules/vime_lightning.py
ts3l/utils/__init__.py
ts3l/utils/base_config.py
ts3l/utils/datamodule.py
ts3l/utils/misc.py
ts3l/utils/backbone_utils/__init__.py
ts3l/utils/backbone_utils/base_backbone_config.py
ts3l/utils/backbone_utils/mlp_backbone_config.py
ts3l/utils/backbone_utils/transformer_config.py
ts3l/utils/dae_utils/__init__.py
ts3l/utils/dae_utils/dae_config.py
ts3l/utils/dae_utils/data_utils.py
ts3l/utils/embedding_utils/__init__.py
ts3l/utils/embedding_utils/base_embedding_config.py
ts3l/utils/embedding_utils/feature_tokenizer_config.py
ts3l/utils/embedding_utils/identity_config.py
ts3l/utils/scarf_utils/__init__.py
ts3l/utils/scarf_utils/data_utils.py
ts3l/utils/scarf_utils/scarf_config.py
ts3l/utils/subtab_utils/__init__.py
ts3l/utils/subtab_utils/data_utils.py
ts3l-0.70.dist-info/LICENSE
ts3l-0.70.dist-info/METADATA
ts3l-0.70.dist-info/WHEEL
ts3l-0.70.dist-info/top_level.txt
ts3l-0.70.dist-info/RECORD
