Metadata-Version: 2.2
Name: ts3l
Version: 0.70
Summary: A PyTorch Lightning-based library for self- and semi-supervised learning on tabular data.
Home-page: https://github.com/Alcoholrithm/TabularS3L
Author: Minwook Kim
Author-email: kmiiiaa@pusan.ac.kr
Keywords: tabular-data semi-supervised-learning self-supervised-learning VIME SubTab SCARF Denoising-AutoEncoder SwitchTab
Requires-Python: >=3.7
License-File: LICENSE
Requires-Dist: numpy
Requires-Dist: pandas
Requires-Dist: scikit-learn
Requires-Dist: torch
Requires-Dist: pytorch_lightning
Requires-Dist: torchmetrics
Dynamic: author
Dynamic: author-email
Dynamic: description
Dynamic: description-content-type
Dynamic: home-page
Dynamic: keywords
Dynamic: requires-dist
Dynamic: requires-python
Dynamic: summary
